bormeparser/__init__.py
bormeparser/acto.py
bormeparser/borme.py
bormeparser/cargo.py
bormeparser/clean.py
bormeparser/config.py
bormeparser/download.py
bormeparser/emisor.py
bormeparser/exceptions.py
bormeparser/parser.py
bormeparser/provincia.py
bormeparser/regex.py
bormeparser/registro.py
bormeparser/seccion.py
bormeparser/sociedad.py
bormeparser/utils.py
bormeparser/backends/__init__.py
bormeparser/backends/base.py
bormeparser/backends/defaults.py
bormeparser/backends/parser1/__init__.py
bormeparser/backends/parser1/functions.py
bormeparser/backends/parser1/parser.py
bormeparser/backends/pypdf2/__init__.py
bormeparser/backends/pypdf2/parser.py
bormeparser/backends/seccion_c/__init__.py
bormeparser/backends/seccion_c/lxml/__init__.py
bormeparser/backends/seccion_c/lxml/parser.py
bormeparser/examples/BORME-A-2015-27-10.pdf
bormeparser/examples/BORME-C-2011-20488.html
bormeparser/examples/BORME-C-2011-20488.xml
bormeparser/examples/BORME-S-20150924.xml
bormeparser-0.5.0.data/data/LICENSE.txt
bormeparser-0.5.0.dist-info/AUTHORS
bormeparser-0.5.0.dist-info/LICENSE.txt
bormeparser-0.5.0.dist-info/METADATA
bormeparser-0.5.0.dist-info/WHEEL
bormeparser-0.5.0.dist-info/top_level.txt
bormeparser-0.5.0.dist-info/RECORD
