Metadata-Version: 2.1
Name: bormeparser
Version: 0.5.0
Summary: bormeparser is a Python library for parsing BORME files
Home-page: https://github.com/PabloCastellano/bormeparser/
Author: Pablo Castellano
Author-email: pablo@anche.no
License: GPLv3+
Download-URL: https://github.com/PabloCastellano/bormeparser/archive/master.zip
Keywords: BORME,transparency,opendata,Spain,Registro mercantil,Boletín Oficial del Registro Mercantil
Platform: UNKNOWN
Classifier: Programming Language :: Python :: 3.6
Classifier: Programming Language :: Python :: 3.7
Classifier: Programming Language :: Python :: 3.8
Requires-Dist: PyPDF2 (==2.11.0)
Requires-Dist: lxml (==4.9.1)
Requires-Dist: pdfminer.six (==20220524)
Requires-Dist: requests (<3.0.0,>=2.22.0)
Requires-Dist: wheel (==0.37.1)
